odoo8_addon_l10n_fr_department_delivery-8.0.0.1.0.99.dev8-py2.7-nspkg.pth
odoo8_addon_l10n_fr_department_delivery-8.0.0.1.0.99.dev8.dist-info/METADATA
odoo8_addon_l10n_fr_department_delivery-8.0.0.1.0.99.dev8.dist-info/RECORD
odoo8_addon_l10n_fr_department_delivery-8.0.0.1.0.99.dev8.dist-info/WHEEL
odoo8_addon_l10n_fr_department_delivery-8.0.0.1.0.99.dev8.dist-info/namespace_packages.txt
odoo8_addon_l10n_fr_department_delivery-8.0.0.1.0.99.dev8.dist-info/top_level.txt
odoo_addons/l10n_fr_department_delivery/README.rst
odoo_addons/l10n_fr_department_delivery/__init__.py
odoo_addons/l10n_fr_department_delivery/__openerp__.py
odoo_addons/l10n_fr_department_delivery/i18n/de.po
odoo_addons/l10n_fr_department_delivery/i18n/es.po
odoo_addons/l10n_fr_department_delivery/i18n/fr.po
odoo_addons/l10n_fr_department_delivery/i18n/it.po
odoo_addons/l10n_fr_department_delivery/i18n/l10n_fr_department_delivery.pot
odoo_addons/l10n_fr_department_delivery/i18n/pt_BR.po
odoo_addons/l10n_fr_department_delivery/i18n/sl.po
odoo_addons/l10n_fr_department_delivery/i18n/tr.po
odoo_addons/l10n_fr_department_delivery/model/__init__.py
odoo_addons/l10n_fr_department_delivery/model/delivery.py
odoo_addons/l10n_fr_department_delivery/static/description/icon.png
odoo_addons/l10n_fr_department_delivery/view/delivery.xml
